LICENSE
MANIFEST.in
README.md
setup.py
keras_hrp/__init__.py
keras_hrp/distance.py
keras_hrp/hrp.py
keras_hrp/serialize.py
keras_hrp.egg-info/PKG-INFO
keras_hrp.egg-info/SOURCES.txt
keras_hrp.egg-info/dependency_links.txt
keras_hrp.egg-info/requires.txt
keras_hrp.egg-info/top_level.txt
keras_hrp.egg-info/zip-safe
test/__init__.py
test/test_distance.py
test/test_hrp.py
test/test_serialize.py