Metadata-Version: 2.1
Name: keras-hrp
Version: 0.2.0
Summary: Hashed Random Projection layer for TF2/Keras
Home-page: http://github.com/ulf1/keras-hrp
Author: Ulf Hamster
Author-email: 554c46@gmail.com
License: Apache License 2.0
Platform: UNKNOWN
Requires-Python: >=3.7
License-File: LICENSE
